fraud_eagle/__init__.py
fraud_eagle/graph.py
fraud_eagle/labels.py
fraud_eagle/likelihood.py
fraud_eagle/prior.py
fraud_eagle/py.typed
rgmining_fraud_eagle-0.10.6.dist-info/METADATA
rgmining_fraud_eagle-0.10.6.dist-info/WHEEL
rgmining_fraud_eagle-0.10.6.dist-info/licenses/COPYING
rgmining_fraud_eagle-0.10.6.dist-info/RECORD
