Metadata-Version: 2.4
Name: rgmining-fraud-eagle
Version: 0.10.6
Summary: An implementation of Fraud Eagle algorithm
License-Expression: GPL-3.0-only
License-File: COPYING
Keywords: algorithm,fraud-eagle,graph,icwsm,mining,review
Author: Junpei Kawamoto
Author-email: kawamoto.junpei@gmail.com
Requires-Python: >=3.11
Classifier: Development Status :: 4 - Beta
Classifier: Intended Audience :: Science/Research
Classifier: License :: OSI Approved :: GNU General Public License v3 (GPLv3)
Classifier: Natural Language :: English
Classifier: Programming Language :: Python
Classifier: Programming Language :: Python :: 3 :: Only
Classifier: Programming Language :: Python :: 3.11
Classifier: Programming Language :: Python :: 3.12
Classifier: Programming Language :: Python :: 3.13
Classifier: Programming Language :: Python :: 3.14
Classifier: Topic :: Scientific/Engineering :: Information Analysis
Classifier: Topic :: Software Development :: Libraries
Requires-Dist: networkx (>=3.2.1)
Requires-Dist: numpy (>=2.2)
Project-URL: Documentation, https://rgmining.github.io/frad-eagle/
Project-URL: Homepage, https://rgmining.github.io/frad-eagle/
Project-URL: Repository, https://github.com/rgmining/frad-eagle
